huvr_client/__init__.py
huvr_client/__version__.py
huvr_client/client.py
huvr_client/exceptions.py
huvr_client/media.py
huvr_client/api/__init__.py
huvr_client/api/assessment_types.py
huvr_client/api/assessments.py
huvr_client/api/asset_types.py
huvr_client/api/assets.py
huvr_client/api/auth.py
huvr_client/api/base_api_module.py
huvr_client/api/checklist_result_lines.py
huvr_client/api/checklist_tasks.py
huvr_client/api/checklist_templates.py
huvr_client/api/checklist_templates_fillable.py
huvr_client/api/checklists.py
huvr_client/api/cmls.py
huvr_client/api/companies.py
huvr_client/api/crews.py
huvr_client/api/defect_profiles.py
huvr_client/api/defects.py
huvr_client/api/heat_data.py
huvr_client/api/inspection_media.py
huvr_client/api/inspection_media_overlays.py
huvr_client/api/libraries.py
huvr_client/api/library_media.py
huvr_client/api/location_layer_profiles.py
huvr_client/api/measurements.py
huvr_client/api/observations_summary.py
huvr_client/api/pages.py
huvr_client/api/project_types.py
huvr_client/api/projects.py
huvr_client/api/recommended_work_plans.py
huvr_client/api/reservations.py
huvr_client/api/schedules.py
huvr_client/api/users.py
huvr_client-0.3.7.dist-info/LICENSE
huvr_client-0.3.7.dist-info/METADATA
huvr_client-0.3.7.dist-info/WHEEL
huvr_client-0.3.7.dist-info/top_level.txt
huvr_client-0.3.7.dist-info/RECORD
