Metadata-Version: 2.1
Name: huvr_client
Version: 0.3.7
Summary: A python client for the HUVRdata API.
Home-page: https://github.com/huvrdata/huvr-client
Author: HUVRdata
Author-email: api@huvrdata.com
Keywords: huvr_client
Classifier: Development Status :: 3 - Alpha
Classifier: Intended Audience :: Developers
Classifier: Natural Language :: English
Classifier: Programming Language :: Python :: 3
Requires-Python: >=3.6
License-File: LICENSE
Requires-Dist: requests
